{
    "Changes": [
        {
            "LogName": "机器",
            "Action": "Load",
            "Target": "Mods/Morepotatoes/animation",
            "FromFile": "assets/Objects/animation.png"
        },
        {
            "LogName": "帽子",
            "Action": "Load",
            "Target": "Mods/Morepotatoes/Hats",
            "FromFile": "assets/Objects/Hats.png"
        },
        {
            "LogName": "物品",
            "Action": "Load",
            "Target": "Mods/Morepotatoes/Objects",
            "FromFile": "assets/Objects/Objects.png"
        },
        {
            "LogName": "帽子",
            "Action": "EditData",
            "Target": "Data/Hats",
            "Entries": {
                "Morepotatoes.potatoesHat": "Morepotatoes.potatoesHat/{{i18n:potatoesHat.de}}/false/true//{{i18n:potatoesHat.name}}/0/assets\\Objects\\Hats",
                "Morepotatoes.budHats": "Morepotatoes.budHats/{{i18n:budHats.de}}/false/true//{{i18n:budHats.name}}/1/assets\\Objects\\Hats",
            }
        },
        {
            "LogName": "炸锅",
            "Action": "EditData",
            "Target": "Data/BigCraftables",
            "Entries": {
                "Morepotatoes.Fryingpan": {
                    "Name": "Morepotatoes.Fryingpan",
                    "DisplayName": "{{i18n:Fryingpan.name}}",
                    "Description": "{{i18n:Fryingpan.de}}",
                    "Price": 500, //价格
                    "CanBePlacedOutDoors": true,
                    "CanBePlacedIndoors": true,
                    "Texture": "Mods/Morepotatoes/animation",
                    "SpriteIndex": 0
                }
            }
        },
        {
            "LogName": "土豆戒指",
            "Action": "EditData",
            "Target": "Data/Objects",
            "Entries": {
                "Morepotatoes.Potatoring": {
                    "Name": "Morepotatoes.Potatoring",
                    "DisplayName": "{{i18n:Potatoring.name}}",
                    "Description": "{{i18n:Potatoring.de}}",
                    "Type": "Ring",
                    "Category": 0,
                    "Price": 0, //价格
                    "Texture": "Mods/Morepotatoes/Objects",
                    "SpriteIndex": 0,
                    "Buffs": null,
                    "ExcludeFromFishingCollection": true,
                    "ExcludeFromShippingCollection": true,
                    "ExcludeFromRandomSale": true,
                    "CustomFields": {
                        "PeacefulEnd.CustomCompanions/Companions/Variety": 2, //最大数量
                        "PeacefulEnd.CustomCompanions/Companions/0/Id": "ExampleAuthor.ExamplePack.ExampleFlyingCompanion", //这应该是companion.json的Name属性的值。
                        "PeacefulEnd.CustomCompanions/Companions/0/NumberToSummon": 1, //这应该是该类型召唤的同伴数量。
                    }
                }
            }
        },
        {
            "LogName": "土豆鱼",
            "Action": "EditData",
            "Target": "Data/Objects",
            "Entries": {
                "Morepotatoes.Potatofish": {
                    "Name": "Morepotatoes.Potatofish",
                    "DisplayName": "{{i18n:Potatofish.name}}",
                    "Description": "{{i18n:Potatofish.de}}",
                    "Type": "Fish",
                    "Category": -4,
                    "Price": 1000,
                    "Texture": "Mods/Morepotatoes/Objects",
                    "SpriteIndex": 0,
                    "Edibility": 50
                }
            }
        },
        {
            "LogName": "油鱼",
            "Action": "EditData",
            "Target": "Data/Objects",
            "Entries": {
                "Morepotatoes.oilfish": {
                    "Name": "Morepotatoes.oilfish",
                    "DisplayName": "{{i18n:oilfish.name}}",
                    "Description": "{{i18n:oilfish.de}}",
                    "Type": "Fish",
                    "Category": -4,
                    "Price": 500,
                    "Texture": "Mods/Morepotatoes/Objects",
                    "SpriteIndex": 0,
                    "Edibility": -50
                }
            }
        },
        {
            "LogName": "土豆淀粉",
            "Action": "EditData",
            "Target": "Data/Objects",
            "Entries": {
                "Morepotatoes.Potatostarch": {
                    "Name": "Morepotatoes.Potatostarch",
                    "Displayname": "{{i18n:Potatostarch.name}}",
                    "Description": "{{i18n:Potatostarch.de}}",
                    "Type": "objects",
                    "Category": 0, //标签
                    "Price": 0, //价格
                    "Edibility": -300,
                    "ExcludeFromRandomSale": "true", //不需要发货
                    "Texture": "Mods/Morepotatoes/Objects", //贴图
                    "SpriteIndex": 0
                }
            }
        },
        {
            "LogName": "沙地马铃薯种子",
            "Action": "EditData",
            "Target": "Data/Objects",
            "Entries": {
                "Morepotatoes.Desertpotatoes_seed": {
                    "Name": "Morepotatoes.Desertpotatoes_seed",
                    "Displayname": "{{i18n:Desertpotatoes_seed.name}}",
                    "Description": "{{i18n:Desertpotatoes_seed.de}}",
                    "Type": "Basic", //蓝底/没蓝底
                    "Category": 0, //标签
                    "Price": 0, //价格
                    "Edibility": -300, //可食性-是不可食用
                    "ExcludeFromRandomSale": "true", //不需要发货
                    "Texture": "Mods/Morepotatoes/Objects", //贴图
                    "SpriteIndex": 0
                }
            }
        },
        {
            "LogName": "沙地马铃薯",
            "Action": "EditData",
            "Target": "Data/Objects",
            "Entries": {
                "Morepotatoes.Desertpotatoes": {
                    "Name": "Morepotatoes.Desertpotatoes",
                    "Displayname": "{{i18n:Desertpotatoes.name}}",
                    "Description": "{{i18n:Desertpotatoes.de}}",
                    "Type": "Basic", //蓝底/没蓝底
                    "Category": 0, //标签
                    "Price": 0, //价格
                    "Edibility": -300, //可食性-是不可食用
                    "ExcludeFromRandomSale": "true", //不需要发货
                    "Texture": "Mods/Morepotatoes/Objects", //贴图
                    "SpriteIndex": 0
                }
            }
        },
        {
            "LogName": "土豆树树苗",
            "Action": "EditData",
            "Target": "Data/Objects",
            "Entries": {
                "Morepotatoes.Potatotree_seed": {
                    "Name": "Morepotatoes.Potatotree_seed",
                    "Displayname": "{{i18n:Potatotree_seed.name}}",
                    "Description": "{{i18n:Potatotree_seed.de}}",
                    "Type": "Basic", //蓝底/没蓝底
                    "Category": 0, //标签
                    "Price": 0, //价格
                    "Edibility": -300, //可食性-是不可食用
                    "ExcludeFromRandomSale": "true", //不需要发货
                    "Texture": "Mods/Morepotatoes/Objects", //贴图
                    "SpriteIndex": 0
                }
            }
        },
        {
            "LogName": "发芽土豆",
            "Action": "EditData",
            "Target": "Data/Objects",
            "Entries": {
                "Morepotatoes.Sproutedpotatoes": {
                    "Name": "Morepotatoes.Sproutedpotatoes",
                    "Displayname": "{{i18n:Sproutedpotatoes.name}}",
                    "Description": "{{i18n:Sproutedpotatoes.de}}",
                    "Type": "objects", //蓝底/没蓝底
                    "Category": 0, //标签
                    "Price": 0, //价格
                    "Edibility": -300, //可食性-是不可食用
                    "ExcludeFromRandomSale": "true", //不需要发货
                    "Texture": "Mods/Morepotatoes/Objects", //贴图
                    "SpriteIndex": 0
                }
            }
        },
        {
            "LogName": "土豆地雷种子",
            "Action": "EditData",
            "Target": "Data/Objects",
            "Entries": {
                "Morepotatoes.PotatoMine_seed": {
                    "Name": "Morepotatoes.PotatoMine_seed",
                    "Displayname": "{{i18n:PotatoMine_seed.name}}",
                    "Description": "{{i18n:PotatoMine_seed.de}}",
                    "Type": "Basic", //蓝底/没蓝底
                    "Category": 0, //标签
                    "Price": 0, //价格
                    "Edibility": -300, //可食性-是不可食用
                    "ExcludeFromRandomSale": "true", //不需要发货
                    "Texture": "Mods/Morepotatoes/Objects", //贴图
                    "SpriteIndex": 0
                }
            }
        },
        {
            "LogName": "土豆地雷",
            "Action": "EditData",
            "Target": "Data/Objects",
            "Entries": {
                "Morepotatoes.PotatoMine": {
                    "Name": "Morepotatoes.PotatoMine",
                    "Displayname": "{{i18n:PotatoMine.name}}",
                    "Description": "{{i18n:PotatoMine.de}}",
                    "Type": "objects", //蓝底/没蓝底
                    "Category": 0, //标签
                    "Price": 0, //价格
                    "Edibility": -300, //可食性-是不可食用
                    "ExcludeFromRandomSale": "true", //不需要发货
                    "Texture": "Mods/Morepotatoes/Objects", //贴图
                    "SpriteIndex": 0,
                    "GeodeDrops": [
                        {
                            "Id": "Morepotatoes.RedPotatoMineCrackedToy",
                            "Chance": 0.1,
                            "Precedence": 0,
                            "Condition": null,
                            "ItemId": null,
                            "RandomItemId": [
                                "(O)113", //Chicken Statue
                                "(O)103", //Ancient Doll
                                "(O)126", //Strange Doll 1
                                "(O)127", //Strange Doll 2
                                "(O)110", //Rusty Spoon
                                "(O)893", //Red Fireworks
                                "(O)894", //Purple Fireworks
                                "(O)895", //You guessed it - Green Fireworks!
                            ]
                        },
                        {
                            "Id": "Morepotatoes.RedMysteryEggCrackedPinkPool",
                            "Chance": 0.33,
                            "Precedence": 0,
                            "Condition": null,
                            "ItemId": "RANDOM_ITEMS (O)",
                            "PerItemCondition": "ITEM_CATEGORY Target -7, ITEM_PRICE Target 80, !ITEM_CONTEXT_TAG Target mt_vapius, !ITEM_ID Target 279"
                        },
                        {
                            "Id": "Morepotatoes.RedMysteryEggCrackedBrownPool",
                            "Chance": 0.5,
                            "Precedence": 0,
                            "Condition": null,
                            "ItemId": "RANDOM_ITEMS (O)",
                            "PerItemCondition": "ITEM_CATEGORY Target -2 -12 -15, ITEM_PRICE Target 100 1700, !ITEM_CONTEXT_TAG Target mt_vapius"
                        },
                        {
                            "Id": "Morepotatoes.RedMysteryEggCrackedGreenPool",
                            "Chance": 1.0,
                            "Precedence": 0,
                            "Condition": null,
                            "ItemId": "RANDOM_ITEMS (O)",
                            "PerItemCondition": "ITEM_CATEGORY Target -75 -79 -80, ITEM_PRICE Target 30 1500, !ITEM_ID Target 454, !ITEM_ID Target lumisteria.crop_tier_3, !ITEM_ID Target stellar_item"
                        }
                    ]
                }
            }
        },
        {
            "LogName": "土豆宝石",
            "Action": "EditData",
            "Target": "Data/Objects",
            "Entries": {
                "Morepotatoes.PotatoGemstone": {
                    "Name": "Morepotatoes.PotatoGemstone",
                    "Displayname": "{{i18n:PotatoGemstone.name}}",
                    "Description": "{{i18n:PotatoGemstone.de}}",
                    "Type": "objects", //蓝底/没蓝底
                    "Category": 0, //标签
                    "Price": 0, //价格
                    "Edibility": -300, //可食性-是不可食用
                    "ExcludeFromRandomSale": "true", //不需要发货
                    "Texture": "Mods/Morepotatoes/Objects", //贴图
                    "SpriteIndex": 0
                }
            }
        },
        {
            "LogName": "古代土豆",
            "Action": "EditData",
            "Target": "Data/Objects",
            "Entries": {
                "Morepotatoes.Ancientpotatoes": {
                    "Name": "Morepotatoes.Ancientpotatoes",
                    "Displayname": "{{i18n:Ancientpotatoes.name}}",
                    "Description": "{{i18n:Ancientpotatoes.de}}",
                    "Type": "Basic", //蓝底/没蓝底
                    "Category": 0, //标签
                    "Price": 0, //价格
                    "Edibility": -300, //可食性-是不可食用
                    "ExcludeFromRandomSale": "true", //不需要发货
                    "Texture": "Mods/Morepotatoes/Objects", //贴图
                    "SpriteIndex": 0
                }
            }
        },
        {
            "LogName": "土豆图腾",
            "Action": "EditData",
            "Target": "Data/Objects",
            "Entries": {
                "Morepotatoes.PotatoTotem": {
                    "Name": "Morepotatoes.PotatoTotem",
                    "DisplayName": "{{i18n:PotatoTotem.name}}",
                    "Description": "{{i18n:PotatoTotem.de}}",
                    "Type": "Crafting",
                    "Category": 0,
                    "Price": 200,
                    "Texture": "Mods/Morepotatoes/Objects",
                    "SpriteIndex": 15,
                    "Edibility": -300,
                    "IsDrink": false,
                    "Buff": null,
                    "GeodeDropsDefaultItems": false,
                    "GeodeDrops": null,
                    "ArtifactSpotChances": null,
                    "ContextTags": [
                        "color_brown",
                        "not_placeable",
                        "totem_item"
                    ],
                    "CustomFields": {}
                }
            }
        },
        {
            "LogName": "土豆图腾传送点",
            "Action": "EditData",
            "Target": "spacechase0.SpaceCore/ObjectExtensionData",
            "Entries": {
                "Morepotatoes.PotatoTotem": {
                    "TotemWarp": {
                        "Location": "1",
                        "Position": "1, 1"
                    }
                }
            }
        },
        {
            "LogName": "薯条围栏",
            "Action": "EditData",
            "Target": "Data/Objects",
            "Entries": {
                "Morepotatoes.Frenchfryfence": {
                    "Name": "Morepotatoes.Frenchfryfence",
                    "Displayname": "{{i18n:Frenchfryfence.name}}",
                    "Description": "{{i18n:Frenchfryfence.de}}",
                    "Type": "Basic", //蓝底/没蓝底
                    "Category": 0, //标签
                    "Price": 0, //价格
                    "Edibility": -300, //可食性-是不可食用
                    "ExcludeFromRandomSale": "true", //不需要发货
                    "Texture": "Mods/Morepotatoes/Objects", //贴图
                    "SpriteIndex": 1
                }
            }
        },
        {
            "LogName": "伏特加",
            "Action": "EditData",
            "Target": "Data/Objects",
            "Entries": {
                "Morepotatoes.vodka": {
                    "Name": "Morepotatoes.vodka",
                    "Displayname": "{{i18n:vodka.name}}",
                    "Description": "{{i18n:vodka.de}}",
                    "Type": "Basic", //有蓝底/没有
                    "Category": -7, //物品标签
                    "Price": 0, //价格
                    "Edibility": 50, //可食性
                    "IsDrink": true,
                    "Buffs": [
                        {
                            "Id": "Food",
                            "BuffId": null,
                            "Duration": 0, //持续时间/游戏内时间
                            "IsDebuff": false, //是负面buff
                            "GlowColor": null,
                            "CustomAttributes": {
                                "FarmingLevel": 0, //耕种
                                "FishingLevel": 0, //钓鱼
                                "MiningLevel": 0, //挖掘
                                "LuckLevel": 0, //幸运
                                "ForagingLevel": 0, //觅食
                                "MaxStamina": 0, //体力
                                "MagneticRadius": 0, //磁力
                                "Speed": 0, //速度
                                "Defense": 0, //防御
                                "Attack": 0
                            }, //攻击
                            "CustomFields": null
                        }
                    ],
                    "Texture": "Mods/Morepotatoes/Objects",
                    "SpriteIndex": 0
                }
            }
        },
        {
            "LogName": "土豆粉",
            "Action": "EditData",
            "Target": "Data/Objects",
            "Entries": {
                "Morepotatoes.Potatopowder": {
                    "Name": "Morepotatoes.Potatopowder",
                    "Displayname": "{{i18n:Potatopowder.name}}",
                    "Description": "{{i18n:Potatopowder.de}}",
                    "Type": "Basic",
                    "Category": -7, //物品标签
                    "Price": 0, //价格
                    "Edibility": 50, //可食性
                    "IsDrink": false, //是饮料
                    "Buffs": [
                        {
                            "Id": "Food",
                            "BuffId": null,
                            "Duration": 0, //持续时间/游戏内时间
                            "IsDebuff": false, //是负面buff
                            "GlowColor": null,
                            "CustomAttributes": {
                                "FarmingLevel": 0, //耕种
                                "FishingLevel": 0, //钓鱼
                                "MiningLevel": 0, //挖掘
                                "LuckLevel": 0, //幸运
                                "ForagingLevel": 0, //觅食
                                "MaxStamina": 0, //体力
                                "MagneticRadius": 0, //磁力
                                "Speed": 0, //速度
                                "Defense": 0, //防御
                                "Attack": 0
                            }, //攻击
                            "CustomFields": null
                        }
                    ],
                    "Texture": "Mods/Morepotatoes/Objects",
                    "SpriteIndex": 0
                }
            }
        },
        {
            "LogName": "三不沾",
            "Action": "EditData",
            "Target": "Data/Objects",
            "Entries": {
                "Morepotatoes.airball": {
                    "Name": "Morepotatoes.airball",
                    "Displayname": "{{i18n:airball.name}}",
                    "Description": "{{i18n:airball.de}}",
                    "Type": "Basic",
                    "Category": -7, //物品标签
                    "Price": 0, //价格
                    "Edibility": 50, //可食性
                    "IsDrink": false, //是饮料
                    "Buffs": [
                        {
                            "Id": "Food",
                            "BuffId": null,
                            "Duration": 0, //持续时间/游戏内时间
                            "IsDebuff": false, //是负面buff
                            "GlowColor": null,
                            "CustomAttributes": {
                                "FarmingLevel": 0, //耕种
                                "FishingLevel": 0, //钓鱼
                                "MiningLevel": 0, //挖掘
                                "LuckLevel": 0, //幸运
                                "ForagingLevel": 0, //觅食
                                "MaxStamina": 0, //体力
                                "MagneticRadius": 0, //磁力
                                "Speed": 0, //速度
                                "Defense": 0, //防御
                                "Attack": 0
                            }, //攻击
                            "CustomFields": null
                        }
                    ],
                    "Texture": "Mods/Morepotatoes/Objects",
                    "SpriteIndex": 0
                }
            }
        },
        {
            "LogName": "土豆炒马铃薯",
            "Action": "EditData",
            "Target": "Data/Objects",
            "Entries": {
                "Morepotatoes.potatoesandpotatoes": {
                    "Name": "Morepotatoes.potatoesandpotatoes",
                    "Displayname": "{{i18n:potatoesandpotatoes.name}}",
                    "Description": "{{i18n:potatoesandpotatoes.de}}",
                    "Type": "Basic",
                    "Category": -7, //物品标签
                    "Price": 0, //价格
                    "Edibility": 50, //可食性
                    "IsDrink": false, //是饮料
                    "Buffs": [
                        {
                            "Id": "Food",
                            "BuffId": null,
                            "Duration": 0, //持续时间/游戏内时间
                            "IsDebuff": false, //是负面buff
                            "GlowColor": null,
                            "CustomAttributes": {
                                "FarmingLevel": 0, //耕种
                                "FishingLevel": 0, //钓鱼
                                "MiningLevel": 0, //挖掘
                                "LuckLevel": 0, //幸运
                                "ForagingLevel": 0, //觅食
                                "MaxStamina": 0, //体力
                                "MagneticRadius": 0, //磁力
                                "Speed": 0, //速度
                                "Defense": 0, //防御
                                "Attack": 0
                            }, //攻击
                            "CustomFields": null
                        }
                    ],
                    "Texture": "Mods/Morepotatoes/Objects",
                    "SpriteIndex": 0
                }
            }
        },
        {
            "LogName": "西红柿条",
            "Action": "EditData",
            "Target": "Data/Objects",
            "Entries": {
                "Morepotatoes.Tomatostrips": {
                    "Name": "Morepotatoes.Tomatostrips",
                    "Displayname": "{{i18n:Tomatostrips.name}}",
                    "Description": "{{i18n:Tomatostrips.de}}",
                    "Type": "Basic",
                    "Category": -7, //物品标签
                    "Price": 0, //价格
                    "Edibility": 50, //可食性
                    "IsDrink": false, //是饮料
                    "Buffs": [
                        {
                            "Id": "Food",
                            "BuffId": null,
                            "Duration": 0, //持续时间/游戏内时间
                            "IsDebuff": false, //是负面buff
                            "GlowColor": null,
                            "CustomAttributes": {
                                "FarmingLevel": 0, //耕种
                                "FishingLevel": 0, //钓鱼
                                "MiningLevel": 0, //挖掘
                                "LuckLevel": 0, //幸运
                                "ForagingLevel": 0, //觅食
                                "MaxStamina": 0, //体力
                                "MagneticRadius": 0, //磁力
                                "Speed": 0, //速度
                                "Defense": 0, //防御
                                "Attack": 0
                            }, //攻击
                            "CustomFields": null
                        }
                    ],
                    "Texture": "Mods/Morepotatoes/Objects",
                    "SpriteIndex": 0
                }
            }
        },
        {
            "LogName": "炸西红柿条",
            "Action": "EditData",
            "Target": "Data/Objects",
            "Entries": {
                "Morepotatoes.Friedtomatostrips": {
                    "Name": "Morepotatoes.Friedtomatostrips",
                    "Displayname": "{{i18n:Friedtomatostrips.name}}",
                    "Description": "{{i18n:Friedtomatostrips.de}}",
                    "Type": "Basic",
                    "Category": -7, //物品标签
                    "Price": 0, //价格
                    "Edibility": 50, //可食性
                    "IsDrink": false, //是饮料
                    "Buffs": [
                        {
                            "Id": "Food",
                            "BuffId": null,
                            "Duration": 0, //持续时间/游戏内时间
                            "IsDebuff": false, //是负面buff
                            "GlowColor": null,
                            "CustomAttributes": {
                                "FarmingLevel": 0, //耕种
                                "FishingLevel": 0, //钓鱼
                                "MiningLevel": 0, //挖掘
                                "LuckLevel": 0, //幸运
                                "ForagingLevel": 0, //觅食
                                "MaxStamina": 0, //体力
                                "MagneticRadius": 0, //磁力
                                "Speed": 0, //速度
                                "Defense": 0, //防御
                                "Attack": 0
                            }, //攻击
                            "CustomFields": null
                        }
                    ],
                    "Texture": "Mods/Morepotatoes/Objects",
                    "SpriteIndex": 0
                }
            }
        },
        {
            "LogName": "姜丝炒土豆丝",
            "Action": "EditData",
            "Target": "Data/Objects",
            "Entries": {
                "Morepotatoes.Gingerandpotatoes": {
                    "Name": "Morepotatoes.Gingerandpotatoes",
                    "Displayname": "{{i18n:Gingerandpotatoes.name}}",
                    "Description": "{{i18n:Gingerandpotatoes.de}}",
                    "Type": "Basic",
                    "Category": -7, //物品标签
                    "Price": 0, //价格
                    "Edibility": 50, //可食性
                    "IsDrink": false, //是饮料
                    "Buffs": [
                        {
                            "Id": "Food",
                            "BuffId": null,
                            "Duration": 0, //持续时间/游戏内时间
                            "IsDebuff": false, //是负面buff
                            "GlowColor": null,
                            "CustomAttributes": {
                                "FarmingLevel": 0, //耕种
                                "FishingLevel": 0, //钓鱼
                                "MiningLevel": 0, //挖掘
                                "LuckLevel": 0, //幸运
                                "ForagingLevel": 0, //觅食
                                "MaxStamina": 0, //体力
                                "MagneticRadius": 0, //磁力
                                "Speed": 0, //速度
                                "Defense": 0, //防御
                                "Attack": 0
                            }, //攻击
                            "CustomFields": null
                        }
                    ],
                    "Texture": "Mods/Morepotatoes/Objects",
                    "SpriteIndex": 0
                }
            }
        },
        {
            "LogName": "糖焗土豆泥",
            "Action": "EditData",
            "Target": "Data/Objects",
            "Entries": {
                "Morepotatoes.mashedpotato": {
                    "Name": "Morepotatoes.mashedpotato",
                    "Displayname": "{{i18n:mashedpotato.name}}",
                    "Description": "{{i18n:mashedpotato.de}}",
                    "Type": "Basic",
                    "Category": -7, //物品标签
                    "Price": 0, //价格
                    "Edibility": 50, //可食性
                    "IsDrink": false, //是饮料
                    "Buffs": [
                        {
                            "Id": "Food",
                            "BuffId": null,
                            "Duration": 0, //持续时间/游戏内时间
                            "IsDebuff": false, //是负面buff
                            "GlowColor": null,
                            "CustomAttributes": {
                                "FarmingLevel": 0, //耕种
                                "FishingLevel": 0, //钓鱼
                                "MiningLevel": 0, //挖掘
                                "LuckLevel": 0, //幸运
                                "ForagingLevel": 0, //觅食
                                "MaxStamina": 0, //体力
                                "MagneticRadius": 0, //磁力
                                "Speed": 0, //速度
                                "Defense": 0, //防御
                                "Attack": 0
                            }, //攻击
                            "CustomFields": null
                        }
                    ],
                    "Texture": "Mods/Morepotatoes/Objects",
                    "SpriteIndex": 0
                }
            }
        },
        {
            "LogName": "烤土豆",
            "Action": "EditData",
            "Target": "Data/Objects",
            "Entries": {
                "Morepotatoes.Bakedpotato": {
                    "Name": "Morepotatoes.Bakedpotato",
                    "Displayname": "{{i18n:Bakedpotato.name}}",
                    "Description": "{{i18n:Bakedpotato.de}}",
                    "Type": "Basic",
                    "Category": -7, //物品标签
                    "Price": 0, //价格
                    "Edibility": 50, //可食性
                    "IsDrink": false, //是饮料
                    "Buffs": [
                        {
                            "Id": "Food",
                            "BuffId": null,
                            "Duration": 0, //持续时间/游戏内时间
                            "IsDebuff": false, //是负面buff
                            "GlowColor": null,
                            "CustomAttributes": {
                                "FarmingLevel": 0, //耕种
                                "FishingLevel": 0, //钓鱼
                                "MiningLevel": 0, //挖掘
                                "LuckLevel": 0, //幸运
                                "ForagingLevel": 0, //觅食
                                "MaxStamina": 0, //体力
                                "MagneticRadius": 0, //磁力
                                "Speed": 0, //速度
                                "Defense": 0, //防御
                                "Attack": 0
                            }, //攻击
                            "CustomFields": null
                        }
                    ],
                    "Texture": "Mods/Morepotatoes/Objects",
                    "SpriteIndex": 0
                }
            }
        },
        {
            "LogName": "脆薯",
            "Action": "EditData",
            "Target": "Data/Objects",
            "Entries": {
                "Morepotatoes.CrispyPotato": {
                    "Name": "Morepotatoes.CrispyPotato",
                    "Displayname": "{{i18n:CrispyPotato.name}}",
                    "Description": "{{i18n:CrispyPotato.de}}",
                    "Type": "Basic",
                    "Category": -7, //物品标签
                    "Price": 0, //价格
                    "Edibility": 50, //可食性
                    "IsDrink": false, //是饮料
                    "Buffs": [
                        {
                            "Id": "Food",
                            "BuffId": null,
                            "Duration": 0, //持续时间/游戏内时间
                            "IsDebuff": false, //是负面buff
                            "GlowColor": null,
                            "CustomAttributes": {
                                "FarmingLevel": 0, //耕种
                                "FishingLevel": 0, //钓鱼
                                "MiningLevel": 0, //挖掘
                                "LuckLevel": 0, //幸运
                                "ForagingLevel": 0, //觅食
                                "MaxStamina": 0, //体力
                                "MagneticRadius": 0, //磁力
                                "Speed": 0, //速度
                                "Defense": 0, //防御
                                "Attack": 0
                            }, //攻击
                            "CustomFields": null
                        }
                    ],
                    "Texture": "Mods/Morepotatoes/Objects",
                    "SpriteIndex": 0
                }
            }
        },
        {
            "LogName": "油炸的{O}",
            "Action": "EditData",
            "Target": "Data/Objects",
            "Entries": {
                "Morepotatoes.Friedones": {
                    "Name": "Morepotatoes.Friedones",
                    "Displayname": "{{i18n:Friedones.name}}",
                    "Description": "{{i18n:Friedones.de}}",
                    "Type": "Basic",
                    "Category": -7, //物品标签
                    "Price": 0, //价格
                    "Edibility": 50, //可食性
                    "IsDrink": false, //是饮料
                    "Buffs": [
                        {
                            "Id": "Food",
                            "BuffId": null,
                            "Duration": 0, //持续时间/游戏内时间
                            "IsDebuff": false, //是负面buff
                            "GlowColor": null,
                            "CustomAttributes": {
                                "FarmingLevel": 0, //耕种
                                "FishingLevel": 0, //钓鱼
                                "MiningLevel": 0, //挖掘
                                "LuckLevel": 0, //幸运
                                "ForagingLevel": 0, //觅食
                                "MaxStamina": 0, //体力
                                "MagneticRadius": 0, //磁力
                                "Speed": 0, //速度
                                "Defense": 0, //防御
                                "Attack": 0
                            }, //攻击
                            "CustomFields": null
                        }
                    ],
                    "Texture": "Mods/Morepotatoes/Objects",
                    "SpriteIndex": 0
                }
            }
        },
    ]
}